.commitlintrc.yaml
.dockerignore
.flake8
.release-please-config.json
.release-please-manifest.json
AUTHORS.md
CHANGELOG.md
CONTRIBUTING.md
Dockerfile
LICENSE
MANIFEST.in
README.md
pyproject.toml
pytest.ini
requirements.txt
run-tests.sh
setup.cfg
setup.py
docs/conf.py
docs/index.md
docs/openapi.json
docs/requirements.txt
reana_server/__init__.py
reana_server/api_client.py
reana_server/app.py
reana_server/cli.py
reana_server/complexity.py
reana_server/config.py
reana_server/decorators.py
reana_server/deleter.py
reana_server/ext.py
reana_server/factory.py
reana_server/fetcher.py
reana_server/gitlab_client.py
reana_server/scheduler.py
reana_server/status.py
reana_server/utils.py
reana_server/validation.py
reana_server/version.py
reana_server.egg-info/PKG-INFO
reana_server.egg-info/SOURCES.txt
reana_server.egg-info/dependency_links.txt
reana_server.egg-info/entry_points.txt
reana_server.egg-info/not-zip-safe
reana_server.egg-info/requires.txt
reana_server.egg-info/top_level.txt
reana_server/reana_admin/__init__.py
reana_server/reana_admin/check_workflows.py
reana_server/reana_admin/cli.py
reana_server/reana_admin/consumer.py
reana_server/reana_admin/options.py
reana_server/reana_admin/retention_rule_deleter.py
reana_server/rest/__init__.py
reana_server/rest/config.py
reana_server/rest/gitlab.py
reana_server/rest/info.py
reana_server/rest/launch.py
reana_server/rest/ping.py
reana_server/rest/secrets.py
reana_server/rest/status.py
reana_server/rest/users.py
reana_server/rest/workflows.py
reana_server/templates/emails/assistance_links.txt
reana_server/templates/emails/email_confirmation.txt
reana_server/templates/emails/token_granted.txt
reana_server/templates/emails/token_request.txt
reana_server/templates/emails/token_revoked.txt
scripts/create-database.sh
scripts/generate_openapi_spec.py
tests/conftest.py
tests/test_cli.py
tests/test_complexity.py
tests/test_decorators.py
tests/test_deleter.py
tests/test_factory.py
tests/test_fetcher.py
tests/test_gitlab_client.py
tests/test_scheduler.py
tests/test_users.py
tests/test_utils.py
tests/test_validation.py
tests/test_version.py
tests/test_views.py
tests/invenio_api/conftest.py
tests/test_files/test_upload.txt