Metadata-Version: 2.2
Name: reana-server
Version: 0.95.0a3
Summary: REANA-Server.
Home-page: https://github.com/reanahub/reana-server
Author: REANA
Author-email: info@reana.io
Classifier: Development Status :: 3 - Alpha
Classifier: Environment :: Web Environment
Classifier: Intended Audience :: Developers
Classifier: License :: OSI Approved :: MIT License
Classifier: Operating System :: OS Independent
Classifier: Programming Language :: Python :: 3
Classifier: Programming Language :: Python :: 3.12
Classifier: Programming Language :: Python :: Implementation :: CPython
Classifier: Programming Language :: Python
Classifier: Programming Language :: Python
Classifier: Topic :: Internet :: WWW/HTTP :: Dynamic Content
Classifier: Topic :: Software Development :: Libraries :: Python Modules
Requires-Python: >=3.8
License-File: LICENSE
License-File: AUTHORS.md
Requires-Dist: Flask<2.3.0,>=2.1.1
Requires-Dist: gitpython>=3.1
Requires-Dist: marshmallow<3.0.0,>2.13.0
Requires-Dist: reana-commons[cwl,kubernetes,snakemake,yadage]<0.96.0,>=0.95.0a9
Requires-Dist: reana-db<0.96.0,>=0.95.0a5
Requires-Dist: requests>=2.25.0
Requires-Dist: tablib>=0.12.1
Requires-Dist: uWSGI>=2.0.17
Requires-Dist: uwsgi-tools>=1.1.1
Requires-Dist: uwsgitop>=0.10
Requires-Dist: wtforms<3.0.0
Requires-Dist: adage==0.11.0
Requires-Dist: packtivity==0.16.2
Requires-Dist: yadage==0.20.1
Requires-Dist: yadage-schemas==0.10.6
Requires-Dist: invenio-app>=1.5.0
Requires-Dist: flask-limiter>=2.3
Requires-Dist: invenio-base>=1.2.0
Requires-Dist: importlib-metadata<5.0.0
Requires-Dist: invenio-cache>=1.1.0
Requires-Dist: invenio-config>=1.0.3
Requires-Dist: invenio-logging>=1.3.0
Requires-Dist: invenio-mail>=1.0.2
Requires-Dist: invenio-accounts>=2.0.0
Requires-Dist: invenio-oauth2server>=1.3.0
Requires-Dist: invenio-oauthclient>=1.5.0
Requires-Dist: invenio-userprofiles>=1.2.0
Requires-Dist: invenio-userprofiles>=1.2.0
Requires-Dist: invenio-theme>=1.4.7
Requires-Dist: invenio-i18n>=1.3.3
Requires-Dist: invenio-access>=2.0.0
Requires-Dist: invenio-db[postgresql]>=1.0.5
Requires-Dist: six>=1.12.0
Provides-Extra: debug
Requires-Dist: wdb; extra == "debug"
Requires-Dist: ipdb; extra == "debug"
Requires-Dist: Flask-DebugToolbar; extra == "debug"
Provides-Extra: docs
Requires-Dist: myst-parser; extra == "docs"
Requires-Dist: Sphinx>=1.5.1; extra == "docs"
Requires-Dist: sphinx-rtd-theme>=0.1.9; extra == "docs"
Requires-Dist: sphinxcontrib-httpdomain>=1.5.0; extra == "docs"
Requires-Dist: sphinxcontrib-openapi>=0.8.0; extra == "docs"
Requires-Dist: sphinxcontrib-redoc>=1.5.1; extra == "docs"
Requires-Dist: sphinx-click>=1.0.4; extra == "docs"
Provides-Extra: tests
Requires-Dist: pytest-reana<0.96.0,>=0.95.0a4; extra == "tests"
Provides-Extra: all
Requires-Dist: wdb; extra == "all"
Requires-Dist: ipdb; extra == "all"
Requires-Dist: Flask-DebugToolbar; extra == "all"
Requires-Dist: myst-parser; extra == "all"
Requires-Dist: Sphinx>=1.5.1; extra == "all"
Requires-Dist: sphinx-rtd-theme>=0.1.9; extra == "all"
Requires-Dist: sphinxcontrib-httpdomain>=1.5.0; extra == "all"
Requires-Dist: sphinxcontrib-openapi>=0.8.0; extra == "all"
Requires-Dist: sphinxcontrib-redoc>=1.5.1; extra == "all"
Requires-Dist: sphinx-click>=1.0.4; extra == "all"
Requires-Dist: pytest-reana<0.96.0,>=0.95.0a4; extra == "all"
Requires-Dist: wdb; extra == "all"
Requires-Dist: ipdb; extra == "all"
Requires-Dist: Flask-DebugToolbar; extra == "all"
Requires-Dist: myst-parser; extra == "all"
Requires-Dist: Sphinx>=1.5.1; extra == "all"
Requires-Dist: sphinx-rtd-theme>=0.1.9; extra == "all"
Requires-Dist: sphinxcontrib-httpdomain>=1.5.0; extra == "all"
Requires-Dist: sphinxcontrib-openapi>=0.8.0; extra == "all"
Requires-Dist: sphinxcontrib-redoc>=1.5.1; extra == "all"
Requires-Dist: sphinx-click>=1.0.4; extra == "all"
Requires-Dist: pytest-reana<0.96.0,>=0.95.0a4; extra == "all"
Dynamic: author
Dynamic: author-email
Dynamic: classifier
Dynamic: description
Dynamic: description-content-type
Dynamic: home-page
Dynamic: provides-extra
Dynamic: requires-dist
Dynamic: requires-python
Dynamic: summary
